gbs/__init__.py
gbs/__main__.py
gbs/command.py
gbs/mode.py
gbs/server.py
gbs-0.1.4.dist-info/LICENSE
gbs-0.1.4.dist-info/METADATA
gbs-0.1.4.dist-info/WHEEL
gbs-0.1.4.dist-info/entry_points.txt
gbs-0.1.4.dist-info/RECORD
