Metadata-Version: 2.1
Name: gbs
Version: 0.1.4
Summary: A Python gopher server.
Home-page: https://github.com/gopherball/gbs
License: MIT
Keywords: gopher,server
Author: Simon de Vlieger
Author-email: cmdr@supakeen.com
Requires-Python: >=3.9,<4
Classifier: License :: OSI Approved :: MIT License
Classifier: Programming Language :: Python
Classifier: Programming Language :: Python :: 3
Classifier: Programming Language :: Python :: 3.9
Classifier: Programming Language :: Python :: 3.10
Classifier: Programming Language :: Python :: 3.11
Classifier: Programming Language :: Python :: 3
Requires-Dist: click (>=8.0,<9.0)
Requires-Dist: gb (>=0.1.3,<0.2.0)
Requires-Dist: tornado (>=6.0,<7.0)
Project-URL: Repository, https://github.com/gopherball/gbs
